pacifica_auth-1.3.0-py3.9-nspkg.pth
pacifica/auth/__init__.py
pacifica/auth/application.py
pacifica/auth/config.py
pacifica/auth/root.py
pacifica/auth/saplugin.py
pacifica/auth/satool.py
pacifica/auth/user_model.py
tests/__init__.py
tests/application_test.py
tests/auth_test.py
tests/check_sa_module_class_test.py
tests/commit_session_test.py
tests/create_argparser_test.py
tests/error_page_test.py
tests/example_test.py
tests/root_test.py
tests/saplugin_test.py
tests/satool_test.py
tests/user_model_test.py
pacifica_auth-1.3.0.dist-info/LICENSE
pacifica_auth-1.3.0.dist-info/METADATA
pacifica_auth-1.3.0.dist-info/WHEEL
pacifica_auth-1.3.0.dist-info/namespace_packages.txt
pacifica_auth-1.3.0.dist-info/top_level.txt
pacifica_auth-1.3.0.dist-info/RECORD
