Metadata-Version: 2.1
Name: pacifica-auth
Version: 1.3.0
Summary: Pacifica Authentication Library
Home-page: https://github.com/pacifica/pacifica-auth/
Author: David Brown
Author-email: dmlb2000@gmail.com
License: UNKNOWN
Platform: UNKNOWN
Requires-Dist: cherrypy
Requires-Dist: sqlalchemy
Requires-Dist: social-auth-core
Requires-Dist: social-auth-app-cherrypy
Requires-Dist: jinja2
